{
    "id": "AspqMa1a",
    "home": {
        "id": "hfAZyE0t",
        "url": "https://www.flashscore.com/team/goias/hfAZyE0t",
        "score": "1"
    },
    "away": {
        "id": "UeD7XtzM",
        "url": "https://www.flashscore.com/team/bahia/UeD7XtzM",
        "score": "1"
    },
    "date": "16.10.2020 20:00",
    "stadium": "Estádio da Serrinha (Goiania)",
    "round": "16",
    "status": "Finished",
    "statistics": {
        "Ball Possession": {
            "home": "53",
            "away": "47"
        },
        "Goal Attempts": {
            "home": "10",
            "away": "13"
        },
        "Shots on Goal": {
            "home": "4",
            "away": "3"
        },
        "Shots off Goal": {
            "home": "4",
            "away": "6"
        },
        "Blocked Shots": {
            "home": "2",
            "away": "4"
        },
        "Free Kicks": {
            "home": "20",
            "away": "17"
        },
        "Corner Kicks": {
            "home": "5",
            "away": "2"
        },
        "Offsides": {
            "home": "1",
            "away": "3"
        },
        "Goalkeeper Saves": {
            "home": "2",
            "away": "3"
        },
        "Fouls": {
            "home": "16",
            "away": "18"
        },
        "Red Cards": {
            "home": "0",
            "away": "1"
        },
        "Yellow Cards": {
            "home": "5",
            "away": "4"
        },
        "Total Passes": {
            "home": "402",
            "away": "348"
        },
        "Tackles": {
            "home": "17",
            "away": "9"
        },
        "Attacks": {
            "home": "130",
            "away": "97"
        },
        "Dangerous Attacks": {
            "home": "36",
            "away": "51"
        }
    }
}