{
    "id": "Gb94A22m",
    "home": {
        "id": "p0JrJCV5",
        "url": "https://www.flashscore.com/team/ceara/p0JrJCV5",
        "score": "2"
    },
    "away": {
        "id": "QBGfQbSe",
        "url": "https://www.flashscore.com/team/corinthians/QBGfQbSe",
        "score": "1"
    },
    "date": "11.10.2020 20:30",
    "stadium": "Castelão (Fortaleza)",
    "round": "15",
    "status": "Finished",
    "statistics": {
        "Ball Possession": {
            "home": "39",
            "away": "61"
        },
        "Goal Attempts": {
            "home": "15",
            "away": "10"
        },
        "Shots on Goal": {
            "home": "4",
            "away": "3"
        },
        "Shots off Goal": {
            "home": "10",
            "away": "4"
        },
        "Blocked Shots": {
            "home": "1",
            "away": "3"
        },
        "Free Kicks": {
            "home": "11",
            "away": "10"
        },
        "Corner Kicks": {
            "home": "6",
            "away": "6"
        },
        "Offsides": {
            "home": "2",
            "away": "1"
        },
        "Goalkeeper Saves": {
            "home": "2",
            "away": "2"
        },
        "Fouls": {
            "home": "9",
            "away": "10"
        },
        "Red Cards": {
            "home": "1",
            "away": "1"
        },
        "Yellow Cards": {
            "home": "4",
            "away": "1"
        },
        "Total Passes": {
            "home": "301",
            "away": "474"
        },
        "Tackles": {
            "home": "10",
            "away": "13"
        },
        "Attacks": {
            "home": "117",
            "away": "92"
        },
        "Dangerous Attacks": {
            "home": "32",
            "away": "31"
        }
    }
}